electronconfig/__init__.py
electronconfig/elconf.py
electronconfig/configurations/electron_configuration.txt
electronconfig-0.1.0.dist-info/LICENSE
electronconfig-0.1.0.dist-info/METADATA
electronconfig-0.1.0.dist-info/WHEEL
electronconfig-0.1.0.dist-info/top_level.txt
electronconfig-0.1.0.dist-info/RECORD
