Metadata-Version: 2.1
Name: electronconfig
Version: 0.1.0
Summary: Electron configuration
Home-page: 
Author: Jakob Olsen
Author-email: jakob.olsen@cern.ch
Classifier: Programming Language :: Python :: 3
Classifier: Operating System :: OS Independent
Requires-Python: >=3.9.0
License-File: LICENSE
Requires-Dist: numpy
Requires-Dist: matplotlib
Requires-Dist: pandas
Provides-Extra: all
Requires-Dist: numpy ; extra == 'all'
Requires-Dist: matplotlib ; extra == 'all'
Requires-Dist: pandas ; extra == 'all'
Provides-Extra: core
Requires-Dist: numpy ; extra == 'core'
Requires-Dist: matplotlib ; extra == 'core'
Requires-Dist: pandas ; extra == 'core'
Provides-Extra: dev
Provides-Extra: doc
Provides-Extra: test
